layer_client/__init__.py
layer_client/client.py
layer_client/config.py
layer_client/exceptions.py
layer_client/api/__init__.py
layer_client/api/ids_pb2.py
layer_client/api/ids_pb2_grpc.py
layer_client/api/entity/__init__.py
layer_client/api/entity/compute_fabric_pb2.py
layer_client/api/entity/compute_fabric_pb2_grpc.py
layer_client/api/entity/data_source_pb2.py
layer_client/api/entity/data_source_pb2_grpc.py
layer_client/api/entity/dataset_build_pb2.py
layer_client/api/entity/dataset_build_pb2_grpc.py
layer_client/api/entity/dataset_list_options_pb2.py
layer_client/api/entity/dataset_list_options_pb2_grpc.py
layer_client/api/entity/dataset_pb2.py
layer_client/api/entity/dataset_pb2_grpc.py
layer_client/api/entity/dataset_version_pb2.py
layer_client/api/entity/dataset_version_pb2_grpc.py
layer_client/api/entity/feature_set_list_options_pb2.py
layer_client/api/entity/feature_set_list_options_pb2_grpc.py
layer_client/api/entity/feature_set_pb2.py
layer_client/api/entity/feature_set_pb2_grpc.py
layer_client/api/entity/model_metric_pb2.py
layer_client/api/entity/model_metric_pb2_grpc.py
layer_client/api/entity/model_pb2.py
layer_client/api/entity/model_pb2_grpc.py
layer_client/api/entity/model_train_pb2.py
layer_client/api/entity/model_train_pb2_grpc.py
layer_client/api/entity/model_version_pb2.py
layer_client/api/entity/model_version_pb2_grpc.py
layer_client/api/entity/paging_pb2.py
layer_client/api/entity/paging_pb2_grpc.py
layer_client/api/entity/sql_feature_pb2.py
layer_client/api/entity/sql_feature_pb2_grpc.py
layer_client/api/entity/user_pb2.py
layer_client/api/entity/user_pb2_grpc.py
layer_client/api/service/__init__.py
layer_client/api/service/datacatalog/__init__.py
layer_client/api/service/datacatalog/data_catalog_api_pb2.py
layer_client/api/service/datacatalog/data_catalog_api_pb2_grpc.py
layer_client/api/service/featureengine/__init__.py
layer_client/api/service/featureengine/feature_engine_api_pb2.py
layer_client-0.3.9.dist-info/METADATA
layer_client-0.3.9.dist-info/WHEEL
layer_client-0.3.9.dist-info/top_level.txt
layer_client-0.3.9.dist-info/RECORD
