Metadata-Version: 2.1
Name: layer-client
Version: 0.3.9
Summary: The Layer Client
Home-page: https://pypi.org/project/layer-client/
Author: The Layer Team
Author-email: python-client@layer.co
License: Apache 2
Platform: UNKNOWN
Requires-Python: >=3.6
Requires-Dist: boto3 (==1.16.24)
Requires-Dist: grpcio-tools (==1.33.2)
Requires-Dist: pandas (==1.1.2)
Requires-Dist: pyspark (==3.0.1)
Requires-Dist: mlflow (==1.12.1)
Provides-Extra: test
